{
  "Id": "podophyllum-peltatum",
  "Description": "",
  "Symptoms": [],
  "Images": [],
  "Names": {
    "Common": "umbrella leaf",
    "Binomial": "podophyllum peltatum",
    "Synonyms": [
      "indian apple root",
      "american mandrake",
      "wild lemon",
      "hog apple",
      "duck's foot",
      "raccoonberry",
      "american mandrake"
    ]
  },
  "Classification": {
    "Kingdom": "",
    "Clade": "",
    "Order": "",
    "Family": "berberidaceae",
    "Genus": "",
    "Species": ""
  }
}
