{"pid":"cannabis-sativa","name":"Cannabis sativa","common":[{"name":"Cannabis","slug":"cannabis"},{"name":"Ruderalis Marijuana","slug":"ruderalis-marijuana"},{"name":"Indica Marijuana","slug":"indica-marijuana"},{"name":"Sativa Marijuana","slug":"sativa-marijuana"}],"symptoms":[{"name":"Depression","slug":"depression"},{"name":"Vomiting","slug":"vomiting"},{"name":"Incoordination","slug":"incoordination"},{"name":"Lethargy","slug":"lethargy"},{"name":"Hyperexcitability","slug":"hyperexcitability"},{"name":"Salivaton","slug":"salivaton"},{"name":"Dilated Pupils","slug":"dilated-pupils"},{"name":"Low Blood Pressure","slug":"low-blood-pressure"},{"name":"Low Body Temperature","slug":"low-body-temperature"},{"name":"Seizure","slug":"seizure"},{"name":"Coma","slug":"coma"},{"name":"Death","slug":"death"}],"date_last_updated":"2023-01-09 14:19:14.208Z","animals":["dogs","cats","horses","reptiles","small-mammals"],"images":[{"relative_path":"images/plants/cannabis-sativa/e32981ad853b8e139494596a76d8e2e3","source_url":"https://inaturalist-open-data.s3.amazonaws.com/photos/78703366/large.jpeg","license":"cc-by-nc","attribution":"(c) karoconniff, some rights reserved (CC BY-NC), uploaded by karoconniff"},{"relative_path":"images/plants/cannabis-sativa/b5bd33e8adf76f63d73e8ed3a8f3450e","source_url":"https://inaturalist-open-data.s3.amazonaws.com/photos/71843/large.jpg","license":"cc-by-nc-sa","attribution":"(c) Dinesh Valke, some rights reserved (CC BY-NC-SA)"},{"relative_path":"images/plants/cannabis-sativa/6fb5e4273738686334007f5a51286ceb","source_url":"https://static.inaturalist.org/photos/46746717/large.jpeg","license":"cc-by-nc","attribution":"(c) Joey Santore, some rights reserved (CC BY-NC), uploaded by Joey Santore"},{"relative_path":"images/plants/cannabis-sativa/cd3806117e7ee37ddd29db14f4b6c1ea","source_url":"https://inaturalist-open-data.s3.amazonaws.com/photos/167717566/large.jpeg","license":"cc-by-nc","attribution":"(c) Martin A. Prinz, some rights reserved (CC BY-NC), uploaded by Martin A. Prinz"},{"relative_path":"images/plants/cannabis-sativa/ca8006731f9095c5ee1f1b325a93be85","source_url":"https://inaturalist-open-data.s3.amazonaws.com/photos/135078207/large.jpg","license":"cc-by-nc","attribution":"(c) Alexander Iosipenko, some rights reserved (CC BY-NC), uploaded by Alexander Iosipenko"},{"relative_path":"images/plants/cannabis-sativa/0af61fd67b45e1e123c0c5597f08528b","source_url":"https://inaturalist-open-data.s3.amazonaws.com/photos/102180473/large.jpg","license":"cc-by","attribution":"(c) Safina Rezeda, some rights reserved (CC BY), uploaded by Safina Rezeda"},{"relative_path":"images/plants/cannabis-sativa/9382dc2f03a90ce27a5eb431c094f207","source_url":"https://inaturalist-open-data.s3.amazonaws.com/photos/151772162/large.jpg","license":"cc-by-nc","attribution":"(c) Martin A. Prinz, some rights reserved (CC BY-NC), uploaded by Martin A. Prinz"},{"relative_path":"images/plants/cannabis-sativa/8fa107f3886d0a024ada3bdfc7d35065","source_url":"https://inaturalist-open-data.s3.amazonaws.com/photos/28813270/large.jpg","license":"cc-by-nc","attribution":"(c) ximena Palma, some rights reserved (CC BY-NC), uploaded by ximena Palma"}],"wikipedia_url":"https://en.wikipedia.org/wiki/Cannabis_sativa","classification":{"kingdom":"","clades":null,"order":"","family":"","genus":"","species":""}}
