{"pid":"dracaena-spp","name":"Dracaena spp.","common":[{"name":"Agave And Allies","slug":"agave-and-allies"},{"name":"Dragon Trees","slug":"dragon-trees"},{"name":"Cornstalk Dracaena","slug":"cornstalk-dracaena"},{"name":"Song Of India","slug":"song-of-india"},{"name":"Madagascar Dragon-Tree","slug":"madagascar-dragon-tree"},{"name":"Lucky Bamboo","slug":"lucky-bamboo"},{"name":"Dragon-Tree","slug":"dragon-tree"},{"name":"Snake Plant","slug":"snake-plant"},{"name":"Large-Leaved Dragon Tree","slug":"large-leaved-dragon-tree"},{"name":"Gold-Dust Dracaena","slug":"gold-dust-dracaena"},{"name":"Mother-In-Law's Tongue","slug":"mother-in-laws-tongue"},{"name":"Mountain Cabbage Tree","slug":"mountain-cabbage-tree"},{"name":"Cambodian Dragon Tree","slug":"cambodian-dragon-tree"},{"name":"Bush Nightfighter","slug":"bush-nightfighter"},{"name":"Lance Dracaena","slug":"lance-dracaena"},{"name":"Dragon Blood Tree","slug":"dragon-blood-tree"},{"name":"Arabian Dragon Tree","slug":"arabian-dragon-tree"},{"name":"Suji","slug":"suji"},{"name":"Hardleaf Asparagus","slug":"hardleaf-asparagus"}],"symptoms":[{"name":"Anorexia","slug":"anorexia"},{"name":"Hypersalivation","slug":"hypersalivation"},{"name":"Dilated Pupils","slug":"dilated-pupils"},{"name":"Abdominal Pain","slug":"abdominal-pain"},{"name":"Increased Heart Rate","slug":"increased-heart-rate"},{"name":"Vomiting","slug":"vomiting"},{"name":"Depression","slug":"depression"},{"name":"Inappetence","slug":"inappetence"},{"name":"Drooling","slug":"drooling"},{"name":"Incoordination","slug":"incoordination"},{"name":"Weakness","slug":"weakness"}],"animals":["dogs","cats","horses","small-mammals"],"images":[{"relative_path":"images/plants/dracaena-sp/f3a52d62843489dfdd7958d9219fc270","source_url":"https://inaturalist-open-data.s3.amazonaws.com/photos/36381403/large.jpeg","license":"cc-by-nc","attribution":"(c) Jesús Niño C., some rights reserved (CC BY-NC), uploaded by Jesús Niño C."},{"relative_path":"images/plants/dracaena-sp/dbedc4488838c42f7a6cd94efe4cf15d","source_url":"https://inaturalist-open-data.s3.amazonaws.com/photos/67527427/large.jpg","license":"cc-by-nc","attribution":"(c) Gina Farr, some rights reserved (CC BY-NC), uploaded by Gina Farr"},{"relative_path":"images/plants/dracaena-sp/b6569eba416b51c7dbc50e940a4b3eee","source_url":"https://inaturalist-open-data.s3.amazonaws.com/photos/111803110/large.jpeg","license":"cc-by","attribution":"(c) Manuel Schwarz, some rights reserved (CC BY), uploaded by Manuel Schwarz"},{"relative_path":"images/plants/dracaena-sp/d345d749d0495e567e66840b4dbb0941","source_url":"https://inaturalist-open-data.s3.amazonaws.com/photos/1004775/large.jpg","license":"cc-by-nc-sa","attribution":"(c) Johannes Lundberg, some rights reserved (CC BY-NC-SA)"},{"relative_path":"images/plants/dracaena-sp/ceced77352afd935a2754e04991b5985","source_url":"https://inaturalist-open-data.s3.amazonaws.com/photos/31035117/large.jpeg","license":"cc-by-nc","attribution":"(c) Craig Peter, some rights reserved (CC BY-NC), uploaded by Craig Peter"},{"relative_path":"images/plants/dracaena-sp/bb292ebd16a3896cebd40fe888668de1","source_url":"https://inaturalist-open-data.s3.amazonaws.com/photos/22183956/large.jpg","license":"cc-by-nc","attribution":"(c) Meghan Magee, some rights reserved (CC BY-NC), uploaded by Meghan Magee"},{"relative_path":"images/plants/dracaena-sp/6d2d4e5d660fe6bfa0b640de6cb46516","source_url":"https://inaturalist-open-data.s3.amazonaws.com/photos/69907178/large.jpg","license":"cc-by-nc","attribution":"(c) Jan Ho, some rights reserved (CC BY-NC), uploaded by Jan Ho"},{"relative_path":"images/plants/dracaena-sp/6522d7353de91aada6f941b424d76617","source_url":"https://inaturalist-open-data.s3.amazonaws.com/photos/89253493/large.jpg","license":"cc-by-nc","attribution":"(c) adityadangwal111, some rights reserved (CC BY-NC)"},{"relative_path":"images/plants/dracaena-sp/a2c11af9dccd326d1ba31af9280f5614","source_url":"https://inaturalist-open-data.s3.amazonaws.com/photos/40223356/large.jpeg","license":"cc-by-nc-sa","attribution":"(c) Marco Schmidt, some rights reserved (CC BY-NC-SA), uploaded by Marco Schmidt"}],"wikipedia_url":"https://en.wikipedia.org/wiki/Dracaena_(plant)","family":"Agavaceae"}
