{"pid":"ligustrum-spp","name":"Ligustrum spp.","common":[{"name":"Privets","slug":"privets"},{"name":"Chinese Privet","slug":"chinese-privet"},{"name":"Tree Privet","slug":"tree-privet"},{"name":"Common Privet","slug":"common-privet"},{"name":"Border Privet","slug":"border-privet"},{"name":"Wax-Leaf Ligustrum","slug":"wax-leaf-ligustrum"},{"name":"Quihoui Privet","slug":"quihoui-privet"},{"name":"Garden Privet","slug":"garden-privet"},{"name":"Scots Lovage","slug":"scots-lovage"},{"name":"Gray's Lovage","slug":"grays-lovage"},{"name":"Mexican Primrose-Willow","slug":"mexican-primrose-willow"},{"name":"Osha","slug":"osha"},{"name":"Japanese Tree Lilac","slug":"japanese-tree-lilac"},{"name":"Hangehange","slug":"hangehange"},{"name":"He-Huckleberry","slug":"he-huckleberry"},{"name":"Celery Leaf Lovage","slug":"celery-leaf-lovage"},{"name":"American Lovage","slug":"american-lovage"},{"name":"Boxleaf Honeysuckle","slug":"boxleaf-honeysuckle"},{"name":"Chilean Potato Vine","slug":"chilean-potato-vine"},{"name":"Hairy Chervil","slug":"hairy-chervil"},{"name":"Canby's Wild Lovage","slug":"canbys-wild-lovage"},{"name":"Hangehange","slug":"hangehange"},{"name":"Gulf Sebastian-Bush","slug":"gulf-sebastian-bush"},{"name":"Fernleaf Licorice-Root","slug":"fernleaf-licorice-root"}],"symptoms":[{"name":"Extreme Stomach Pain","slug":"extreme-stomach-pain"},{"name":"Abdominal Pain","slug":"abdominal-pain"},{"name":"Hyper Salivaton","slug":"hyper-salivaton"},{"name":"Salivation","slug":"salivation"},{"name":"Skin Irritation","slug":"skin-irritation"},{"name":"Difficulty Breathing","slug":"difficulty-breathing"},{"name":"Cardiac Failure","slug":"cardiac-failure"}],"date_last_updated":"2023-01-09 14:19:16.996Z","animals":["hamsters"],"images":[{"relative_path":"images/plants/ligustrum-spp/e4bce9dd562df97c3de40f08e2d9c21a","source_url":"https://inaturalist-open-data.s3.amazonaws.com/photos/126520804/large.jpeg","license":"cc-by-nc","attribution":"(c) pileatedtree, some rights reserved (CC BY-NC), uploaded by pileatedtree"},{"relative_path":"images/plants/ligustrum-spp/63bd566d26308d85b0c786d2529b1dc4","source_url":"https://inaturalist-open-data.s3.amazonaws.com/photos/71791708/large.jpg","license":"cc-by-nc","attribution":"(c) Kate Goodenough, some rights reserved (CC BY-NC), uploaded by Kate Goodenough"},{"relative_path":"images/plants/ligustrum-spp/a48cf0b6ecb7fd9664a9f59cf746635f","source_url":"https://inaturalist-open-data.s3.amazonaws.com/photos/30963096/large.jpg","license":"cc-by-nc","attribution":"(c) Bill Wright, some rights reserved (CC BY-NC), uploaded by Bill Wright"},{"relative_path":"images/plants/ligustrum-spp/ced86e26ce1303dc0e858ad6b88feaef","source_url":"https://inaturalist-open-data.s3.amazonaws.com/photos/28606/large.jpg","license":"cc-by-nc-sa","attribution":"(c) Arthur Chapman, some rights reserved (CC BY-NC-SA)"},{"relative_path":"images/plants/ligustrum-spp/bc0260df4de5ecfc46cfb44be137b3e8","source_url":"https://inaturalist-open-data.s3.amazonaws.com/photos/57418669/large.jpeg","license":"cc-by-nc","attribution":"(c) John C., some rights reserved (CC BY-NC), uploaded by John C."},{"relative_path":"images/plants/ligustrum-spp/84f7fb24ae641c239d18710d66f77516","source_url":"https://inaturalist-open-data.s3.amazonaws.com/photos/570026/large.jpg","license":"cc-by-nc-sa","attribution":"(c) Kai Yan,  Joseph Wong, some rights reserved (CC BY-NC-SA)"},{"relative_path":"images/plants/ligustrum-spp/e5d3ef69ce59a7c27d7792cc42216a2e","source_url":"https://inaturalist-open-data.s3.amazonaws.com/photos/57565818/large.jpeg","license":"cc-by-nc","attribution":"(c) John C., some rights reserved (CC BY-NC), uploaded by John C."},{"relative_path":"images/plants/ligustrum-spp/f1d76c2c9b0cbbab2975d7db8145201e","source_url":"https://static.inaturalist.org/photos/79702702/large.jpg","license":"cc-by-sa","attribution":"(c) Doug Beckers, some rights reserved (CC BY-SA)"},{"relative_path":"images/plants/ligustrum-spp/eaa4b2bdbe6f4a8baa3509d05798d9cf","source_url":"https://inaturalist-open-data.s3.amazonaws.com/photos/34958873/large.jpg","license":"cc-by-nc","attribution":"(c) jessiex47, some rights reserved (CC BY-NC), uploaded by jessiex47"}],"wikipedia_url":"http://en.wikipedia.org/wiki/Privet","classification":{"kingdom":"Plantae","clades":["Tracheophytes","Angiosperms","Eudicots","Asterids"],"order":"Lamiales","family":"Oleaceae","genus":"LigustrumL.","species":""}}
