{"pid":"melia-azedarach","name":"Melia azedarach","common":[{"name":"Chinaberry","slug":"chinaberry"}],"symptoms":[{"name":"Diarrhea","slug":"diarrhea"},{"name":"Vomiting","slug":"vomiting"},{"name":"Hypersalivation","slug":"hypersalivation"},{"name":"Depression","slug":"depression"},{"name":"Weakness","slug":"weakness"},{"name":"Seizures","slug":"seizures"}],"date_last_updated":"2023-01-09 14:19:19.198Z","animals":["dogs","cats","horses","birds","small-mammals"],"images":[{"relative_path":"images/plants/melia-azedarach/53db144bf2c09c1d35836e2973a38b63","source_url":"https://inaturalist-open-data.s3.amazonaws.com/photos/33351307/large.jpeg","license":"cc-by-nc","attribution":"(c) 葉子, some rights reserved (CC BY-NC), uploaded by 葉子"},{"relative_path":"images/plants/melia-azedarach/c21c19a91da7740ff791636e16db8343","source_url":"https://inaturalist-open-data.s3.amazonaws.com/photos/38231340/large.jpeg","license":"cc-by-nc","attribution":"(c) Giuseppe Buscemi, some rights reserved (CC BY-NC), uploaded by Giuseppe Buscemi"},{"relative_path":"images/plants/melia-azedarach/170745e7447ea6da410e99c3172285d1","source_url":"https://inaturalist-open-data.s3.amazonaws.com/photos/60005429/large.jpg","license":"cc-by","attribution":"(c) Don Loarie, some rights reserved (CC BY), uploaded by Don Loarie"},{"relative_path":"images/plants/melia-azedarach/ed76eaea9862dedf88a91b974047919b","source_url":"https://inaturalist-open-data.s3.amazonaws.com/photos/1838023/large.jpg","license":"cc-by-nc","attribution":"(c) Milo Pyne, some rights reserved (CC BY-NC), uploaded by Milo Pyne"},{"relative_path":"images/plants/melia-azedarach/766223a1f6f503ccb4cf51e92814bd3b","source_url":"https://inaturalist-open-data.s3.amazonaws.com/photos/59896161/large.jpeg","license":"cc-by-nc","attribution":"(c) 葉子, some rights reserved (CC BY-NC), uploaded by 葉子"},{"relative_path":"images/plants/melia-azedarach/fb95527d7294676cf1d3812de45d64e5","source_url":"https://inaturalist-open-data.s3.amazonaws.com/photos/60005412/large.jpg","license":"cc-by","attribution":"(c) Don Loarie, some rights reserved (CC BY), uploaded by Don Loarie"},{"relative_path":"images/plants/melia-azedarach/23df90bd790c06b3fdf54a2e65d16e7d","source_url":"https://inaturalist-open-data.s3.amazonaws.com/photos/21234416/large.jpg","license":"cc-by-nc","attribution":"(c) maddie_b, some rights reserved (CC BY-NC), uploaded by maddie_b"},{"relative_path":"images/plants/melia-azedarach/0e675043c532d8026575d7285497d003","source_url":"https://inaturalist-open-data.s3.amazonaws.com/photos/7251513/large.jpg","license":"cc0","attribution":"no rights reserved, uploaded by Jaime González"},{"relative_path":"images/plants/melia-azedarach/a6e7a3a01a19e379fd51c8b896158387","source_url":"https://inaturalist-open-data.s3.amazonaws.com/photos/61655934/large.jpg","license":"cc-by-nc","attribution":"(c) Curtis Endicott, some rights reserved (CC BY-NC), uploaded by Curtis Endicott"}],"wikipedia_url":"https://en.wikipedia.org/wiki/Melia_azedarach"}
