{"pid":"astragalus-spp","name":"Astragalus spp.","common":[{"name":"Milkvetches","slug":"milkvetches"},{"name":"Wild Liquorice","slug":"wild-liquorice"},{"name":"Chickpea Milkvetch","slug":"chickpea-milkvetch"},{"name":"Santa Barbara Milkvetch","slug":"santa-barbara-milkvetch"},{"name":"Freckled Milkvetch","slug":"freckled-milkvetch"},{"name":"Woollypod Milkvetch","slug":"woollypod-milkvetch"},{"name":"Alpine Milkvetch","slug":"alpine-milkvetch"},{"name":"Ground-Plum","slug":"ground-plum"},{"name":"Canadian Milkvetch","slug":"canadian-milkvetch"},{"name":"Purple Milk-Vetch","slug":"purple-milk-vetch"},{"name":"Woolly Locoweed","slug":"woolly-locoweed"},{"name":"Nuttall's Milkvetch","slug":"nuttalls-milkvetch"},{"name":"Saintfoin Milk Vetch","slug":"saintfoin-milk-vetch"},{"name":"Douglas' Milkvetch","slug":"douglas-milkvetch"},{"name":"Southern California Milkvetch","slug":"southern-california-milkvetch"},{"name":"Small-Flowered Milkvetch","slug":"small-flowered-milkvetch"},{"name":"Field Milkvetch","slug":"field-milkvetch"},{"name":"Timber Milkvetch","slug":"timber-milkvetch"},{"name":"Missouri Milkvetch","slug":"missouri-milkvetch"},{"name":"Laxmann's Milkvetch","slug":"laxmanns-milkvetch"},{"name":"Montpelier Milkvetch","slug":"montpelier-milkvetch"},{"name":"Two-Grooved Milkvetch","slug":"two-grooved-milkvetch"},{"name":"Balloon Milkvetch","slug":"balloon-milkvetch"},{"name":"Utah Milkvetch","slug":"utah-milkvetch"},{"name":"Drummond's Milkvetch","slug":"drummonds-milkvetch"},{"name":"Early Purple Milkvetch","slug":"early-purple-milkvetch"},{"name":"Southern Milkvetch","slug":"southern-milkvetch"},{"name":"Palmer's Milkvetch","slug":"palmers-milkvetch"},{"name":"Torrey's Milkvetch","slug":"torreys-milkvetch"}],"symptoms":[{"name":"Drooling","slug":"drooling"},{"name":"Vomiting","slug":"vomiting"},{"name":"Diarrhea","slug":"diarrhea"},{"name":"Lethargy","slug":"lethargy"},{"name":"Respiratory Depression","slug":"respiratory-depression"},{"name":"Dry Heaving","slug":"dry-heaving"}],"date_last_updated":"2023-01-09 15:23:37.686Z","animals":["reptiles","hamsters"],"images":[{"relative_path":"images/plants/astragalus-spp/e84dad2fc4f2e3c14185b0243520038f","source_url":"https://inaturalist-open-data.s3.amazonaws.com/photos/41516152/original.jpg","license":"cc-by-nc","attribution":"(c) Corey Lange, some rights reserved (CC BY-NC), uploaded by Corey Lange"},{"relative_path":"images/plants/astragalus-spp/f9189e821f177d4c282b070dfdba3fe3","source_url":"https://inaturalist-open-data.s3.amazonaws.com/photos/63428865/original.jpg","license":"cc-by-nc","attribution":"(c) kathleen_hughes, some rights reserved (CC BY-NC)"},{"relative_path":"images/plants/astragalus-spp/79f8082e7cfddec3671c2d909156de11","source_url":"https://inaturalist-open-data.s3.amazonaws.com/photos/33705240/original.jpeg","license":"cc0","attribution":"no rights reserved, uploaded by Alex Heyman"},{"relative_path":"images/plants/astragalus-spp/89504851ca721bb39a63c3705d7c2441","source_url":"https://inaturalist-open-data.s3.amazonaws.com/photos/106212396/original.jpg","license":"cc-by-nc","attribution":"(c) petr_kosachev, some rights reserved (CC BY-NC), uploaded by petr_kosachev"},{"relative_path":"images/plants/astragalus-spp/82cd8b51d56de09801302655ea0206e7","source_url":"https://static.inaturalist.org/photos/108439776/original.jpg","license":"cc-by-sa","attribution":"(c) Stan Shebs, some rights reserved (CC BY-SA)"},{"relative_path":"images/plants/astragalus-spp/d252b2ca4812f3c481a3574168608850","source_url":"https://inaturalist-open-data.s3.amazonaws.com/photos/13385/original.jpg","license":"cc-by-sa","attribution":"(c) Matt Lavin, some rights reserved (CC BY-SA)"},{"relative_path":"images/plants/astragalus-spp/c0b2dbce99f05f9a2b7543c65041fd8a","source_url":"https://static.inaturalist.org/photos/108439777/original.jpg","license":"cc-by-sa","attribution":"(c) Matt Lavin, some rights reserved (CC BY-SA)"},{"relative_path":"images/plants/astragalus-spp/7fd3e4d60b272d02ff0bb5d3939d1b24","source_url":"https://inaturalist-open-data.s3.amazonaws.com/photos/30330785/original.jpg","license":"cc-by-nc","attribution":"(c) Sergey Mayorov, some rights reserved (CC BY-NC), uploaded by Sergey Mayorov"},{"relative_path":"images/plants/astragalus-spp/e9b723532aecd7b43d248e8134ecd34a","source_url":"https://inaturalist-open-data.s3.amazonaws.com/photos/66272591/original.jpg","license":"cc-by-nc","attribution":"(c) Pyak Andrei, some rights reserved (CC BY-NC), uploaded by Pyak Andrei"}],"wikipedia_url":"http://en.wikipedia.org/wiki/Astragalus","classification":{"kingdom":"Plantae","clades":["Tracheophytes","Angiosperms","Eudicots","Rosids"],"order":"Fabales","family":"Fabaceae","genus":"AstragalusL.","species":""}}
