{"id":"dracaena-sp","name":"Dracaena sp.","common":["Straight-Marginated Dracaena","Song of India","Song of Jamaica","Warneckii","Janet Craig Plant","Corn Plant","Cornstalk Plant","Dracaena","Dragon Tree","Ribbon Plant"],"date_last_updated":"2022-12-19T14:55:10.000Z","animals":["dog","cat"],"images":[{"url":"plants/dracaena-sp/images/1.jpg","source_url":"https://inaturalist-open-data.s3.amazonaws.com/photos/36381403/medium.jpeg","license":"cc-by-nc","attribution":"(c) Jesús Niño C., some rights reserved (CC BY-NC), uploaded by Jesús Niño C."},{"url":"plants/dracaena-sp/images/2.jpg","source_url":"https://inaturalist-open-data.s3.amazonaws.com/photos/67527427/medium.jpg","license":"cc-by-nc","attribution":"(c) Gina Farr, some rights reserved (CC BY-NC), uploaded by Gina Farr"},{"url":"plants/dracaena-sp/images/3.jpg","source_url":"https://inaturalist-open-data.s3.amazonaws.com/photos/111803110/medium.jpeg","license":"cc-by","attribution":"(c) Manuel Schwarz, some rights reserved (CC BY), uploaded by Manuel Schwarz"},{"url":"plants/dracaena-sp/images/4.jpg","source_url":"https://inaturalist-open-data.s3.amazonaws.com/photos/1004775/medium.jpg","license":"cc-by-nc-sa","attribution":"(c) Johannes Lundberg, some rights reserved (CC BY-NC-SA)"},{"url":"plants/dracaena-sp/images/5.jpg","source_url":"https://inaturalist-open-data.s3.amazonaws.com/photos/1004775/medium.jpg","license":"cc-by-nc-sa","attribution":"(c) Johannes Lundberg, some rights reserved (CC BY-NC-SA)"},{"url":"plants/dracaena-sp/images/6.jpg","source_url":"https://inaturalist-open-data.s3.amazonaws.com/photos/31035117/medium.jpeg","license":"cc-by-nc","attribution":"(c) Craig Peter, some rights reserved (CC BY-NC), uploaded by Craig Peter"},{"url":"plants/dracaena-sp/images/7.jpg","source_url":"https://inaturalist-open-data.s3.amazonaws.com/photos/22183956/medium.jpg","license":"cc-by-nc","attribution":"(c) Meghan Magee, some rights reserved (CC BY-NC), uploaded by Meghan Magee"},{"url":"plants/dracaena-sp/images/8.jpg","source_url":"https://inaturalist-open-data.s3.amazonaws.com/photos/69907178/medium.jpg","license":"cc-by-nc","attribution":"(c) Jan Ho, some rights reserved (CC BY-NC), uploaded by Jan Ho"},{"url":"plants/dracaena-sp/images/9.jpg","source_url":"https://inaturalist-open-data.s3.amazonaws.com/photos/89253493/medium.jpg","license":"cc-by-nc","attribution":"(c) adityadangwal111, some rights reserved (CC BY-NC)"},{"url":"plants/dracaena-sp/images/10.jpg","source_url":"https://inaturalist-open-data.s3.amazonaws.com/photos/40223356/medium.jpeg","license":"cc-by-nc-sa","attribution":"(c) Marco Schmidt, some rights reserved (CC BY-NC-SA), uploaded by Marco Schmidt"},{"url":"plants/dracaena-sp/images/11.jpg","source_url":"https://inaturalist-open-data.s3.amazonaws.com/photos/58748987/medium.jpg","license":"cc-by-nc","attribution":"(c) Shiwalee Samant, some rights reserved (CC BY-NC), uploaded by Shiwalee Samant"},{"url":"plants/dracaena-sp/images/12.jpg","source_url":"https://inaturalist-open-data.s3.amazonaws.com/photos/715973/medium.JPG","license":"cc-by-nc-sa","attribution":"(c) 106611639464075912591, some rights reserved (CC BY-NC-SA), uploaded by 106611639464075912591"}],"symptoms":["anorexia","hypersalivation","dilated pupils","abdominal pain","increased heart rate","vomiting","depression","inappetence","drooling","incoordination","weakness"],"source_url":"","wikipedia_url":"https://en.wikipedia.org/wiki/Dracaena_(plant)","classification":{"kingdom":"Plantae","clades":["Tracheophytes","Angiosperms","Monocots"],"order":"Asparagales","family":"Agavaceae","genus":"Dracaena","species":""}}
