{"pid":"phytolacca-americana","name":"Phytolacca Americana","common":[{"name":"American Pokeweed","slug":"american-pokeweed"},{"name":"Common American Pokeweed","slug":"common-american-pokeweed"},{"name":"Maritime Pokeweed","slug":"maritime-pokeweed"},{"name":"Inkweed","slug":"inkweed"}],"symptoms":[{"name":"Drooling","slug":"drooling"},{"name":"Vomiting","slug":"vomiting"},{"name":"Diarrhea","slug":"diarrhea"},{"name":"Lethargy","slug":"lethargy"},{"name":"Respiratory Depression","slug":"respiratory-depression"},{"name":"Dry Heaving","slug":"dry-heaving"}],"date_last_updated":"2023-01-09 15:23:38.724Z","animals":["reptiles","rats"],"images":[{"relative_path":"images/plants/phytolacca-americana/278f26afc4f6c4f94cf832fba36f4d80","source_url":"https://inaturalist-open-data.s3.amazonaws.com/photos/164206478/original.jpeg","license":"cc-by-nc-nd","attribution":"(c) Craig K. Hunt, some rights reserved (CC BY-NC-ND), uploaded by Craig K. Hunt"},{"relative_path":"images/plants/phytolacca-americana/0e314aad9fea62cc45a7235fa248c2fc","source_url":"https://inaturalist-open-data.s3.amazonaws.com/photos/49290257/original.jpg","license":"cc-by-nc","attribution":"(c) barburk, some rights reserved (CC BY-NC)"},{"relative_path":"images/plants/phytolacca-americana/d2f87a98782637834f8b98acb66df50e","source_url":"https://inaturalist-open-data.s3.amazonaws.com/photos/79055906/original.jpg","license":"cc-by-nc","attribution":"(c) Joan Costanza, some rights reserved (CC BY-NC), uploaded by Joan Costanza"},{"relative_path":"images/plants/phytolacca-americana/285a98427a1ce92e477c9ac811bd29be","source_url":"https://inaturalist-open-data.s3.amazonaws.com/photos/53608914/original.jpg","license":"cc-by","attribution":"(c) Sandy Wolkenberg, some rights reserved (CC BY), uploaded by Sandy Wolkenberg"},{"relative_path":"images/plants/phytolacca-americana/061586784172e60b6e2e33b4160dca37","source_url":"https://inaturalist-open-data.s3.amazonaws.com/photos/149703539/original.jpeg","license":"cc0","attribution":"no rights reserved, uploaded by Bram vd Bergh"},{"relative_path":"images/plants/phytolacca-americana/b53c1bc61b4f55bc1748bf4cf0ffe1ff","source_url":"https://inaturalist-open-data.s3.amazonaws.com/photos/204384348/original.jpg","license":"cc-by-nc","attribution":"(c) Douglas Goldman, some rights reserved (CC BY-NC), uploaded by Douglas Goldman"},{"relative_path":"images/plants/phytolacca-americana/84f5a19c85085649d98fc2b39bd4ac61","source_url":"https://inaturalist-open-data.s3.amazonaws.com/photos/84277904/original.jpg","license":"cc-by-nc","attribution":"(c) Megan Nippa, some rights reserved (CC BY-NC), uploaded by Megan Nippa"},{"relative_path":"images/plants/phytolacca-americana/2797fc0c17b73a9f68302fb16b8d9ce8","source_url":"https://inaturalist-open-data.s3.amazonaws.com/photos/2420278/original.JPG","license":"cc-by-nc-nd","attribution":"(c) Mark Kluge, some rights reserved (CC BY-NC-ND), uploaded by Mark Kluge"},{"relative_path":"images/plants/phytolacca-americana/09d8a61b7425ec63afb5963f5eb496d7","source_url":"https://inaturalist-open-data.s3.amazonaws.com/photos/11635183/original.jpg","license":"cc-by-nc","attribution":"(c) Pat Deacon, some rights reserved (CC BY-NC), uploaded by Pat Deacon"}],"wikipedia_url":"http://en.wikipedia.org/wiki/Phytolacca_americana"}
