{"pid":"ranunculus-spp","name":"Ranunculus spp.","common":[{"name":"Buttercups, Poppies, And Allies","slug":"buttercups-poppies-and-allies"},{"name":"Buttercups","slug":"buttercups"},{"name":"Buttercup Family","slug":"buttercup-family"},{"name":"Anemones, Buttercups, Larkspurs And Allies","slug":"anemones-buttercups-larkspurs-and-allies"},{"name":"Creeping Buttercup","slug":"creeping-buttercup"},{"name":"Meadow Buttercup","slug":"meadow-buttercup"},{"name":"Bulbous Buttercup","slug":"bulbous-buttercup"},{"name":"Small-Flowered Buttercup","slug":"small-flowered-buttercup"},{"name":"Cursed Crowfoot","slug":"cursed-crowfoot"},{"name":"California Buttercup","slug":"california-buttercup"},{"name":"Bristly Buttercup","slug":"bristly-buttercup"},{"name":"Hooked Buttercup","slug":"hooked-buttercup"},{"name":"Lesser Celandine","slug":"lesser-celandine"},{"name":"Subgenus Ranunculus","slug":"subgenus-ranunculus"},{"name":"Western Buttercup","slug":"western-buttercup"},{"name":"Goldilocks Buttercup","slug":"goldilocks-buttercup"},{"name":"Lesser Spearwort","slug":"lesser-spearwort"},{"name":"Rough-Fruited Buttercup","slug":"rough-fruited-buttercup"},{"name":"Multi-Flowered Buttercup","slug":"multi-flowered-buttercup"},{"name":"Hairy Buttercup","slug":"hairy-buttercup"},{"name":"Kashubian Buttercups","slug":"kashubian-buttercups"},{"name":"Common Water-Crowfoot","slug":"common-water-crowfoot"},{"name":"Early Buttercup","slug":"early-buttercup"},{"name":"Sagebrush Buttercup","slug":"sagebrush-buttercup"},{"name":"Woolly Buttercup","slug":"woolly-buttercup"},{"name":"Woodland Buttercup","slug":"woodland-buttercup"},{"name":"Yellow Anemone","slug":"yellow-anemone"},{"name":"Chinese Buttercup","slug":"chinese-buttercup"},{"name":"Glacier Crowfoot","slug":"glacier-crowfoot"}],"symptoms":[{"name":"Vomiting","slug":"vomiting"},{"name":"Diarrhea","slug":"diarrhea"},{"name":"Depression","slug":"depression"},{"name":"Anorexia","slug":"anorexia"},{"name":"Hypersalivation","slug":"hypersalivation"},{"name":"Oral Ulcers","slug":"oral-ulcers"},{"name":"Incoordination","slug":"incoordination"}],"date_last_updated":"2023-01-09 14:19:20.446Z","animals":["dogs","cats","horses","reptiles","rats","rabbits","hamsters"],"images":[{"relative_path":"images/plants/ranunculus-spp/822ea64576daf1844de594b79ac7fe31","source_url":"https://inaturalist-open-data.s3.amazonaws.com/photos/10459/large.jpg","license":"cc-by-nc-sa","attribution":"(c) Cody Hough, some rights reserved (CC BY-NC-SA)"},{"relative_path":"images/plants/ranunculus-spp/a4fb033b04844dc9c56bd40f35edd35a","source_url":"https://static.inaturalist.org/photos/58232120/large.jpg","license":"cc-by-nc-sa","attribution":"(c) Apus wd, some rights reserved (CC BY-NC-SA)"},{"relative_path":"images/plants/ranunculus-spp/6f4b4e21e2c1d6c78b5cd4dcdd58d5d8","source_url":"https://static.inaturalist.org/photos/58232459/large.jpg","license":"cc-by-sa","attribution":"(c) Andrew Curtis, some rights reserved (CC BY-SA)"},{"relative_path":"images/plants/ranunculus-spp/b8c731605d778e7618db5b03d6483ad3","source_url":"https://static.inaturalist.org/photos/58232514/large.jpg","license":"cc-by-nc-nd","attribution":"(c) Courtney McGough, some rights reserved (CC BY-NC-ND)"},{"relative_path":"images/plants/ranunculus-spp/d72ab49357083fe59ee70a85fb09f0b6","source_url":"https://static.inaturalist.org/photos/58232534/large.jpg","license":"cc-by-nc-sa","attribution":"(c) Arb O'Retum, some rights reserved (CC BY-NC-SA)"},{"relative_path":"images/plants/ranunculus-spp/756d647a59e9ba10576d573a67decc3d","source_url":"https://static.inaturalist.org/photos/58232580/large.jpg","license":"cc-by-sa","attribution":"(c) 阿橋 HQ, some rights reserved (CC BY-SA)"},{"relative_path":"images/plants/ranunculus-spp/ce47f5acbabce4351dfb55459374320b","source_url":"https://inaturalist-open-data.s3.amazonaws.com/photos/33432754/large.jpeg","license":"cc-by-nc","attribution":"(c) mintren, some rights reserved (CC BY-NC), uploaded by mintren"},{"relative_path":"images/plants/ranunculus-spp/662422320296b069d519940062b4541e","source_url":"https://static.inaturalist.org/photos/8922702/large.jpg","license":"cc-by","attribution":"(c) Whitney Brook Matson, some rights reserved (CC BY), uploaded by Whitney Brook Matson"},{"relative_path":"images/plants/ranunculus-spp/30879c3ed7ebe956aa4a7fc7d1d5c839","source_url":"https://static.inaturalist.org/photos/53566757/large.jpeg","license":"cc-by","attribution":"(c) Dmitry Kulakov, some rights reserved (CC BY), uploaded by Dmitry Kulakov"}],"wikipedia_url":"https://en.wikipedia.org/wiki/Ranunculus","classification":{"kingdom":"Plantae","clades":["Tracheophytes","Angiosperms","Eudicots"],"order":"Ranunculales","family":"Ranunculaceae","genus":"Ranunculus","species":""}}
